main.py
discord_webhook_example_kurtcobain-0.0.1.dist-info/METADATA
discord_webhook_example_kurtcobain-0.0.1.dist-info/WHEEL
discord_webhook_example_kurtcobain-0.0.1.dist-info/top_level.txt
discord_webhook_example_kurtcobain-0.0.1.dist-info/RECORD
