Metadata-Version: 2.1
Name: discord-webhook-example-kurtcobain
Version: 0.0.1
Summary: testing with webhooks
